Workbook

Sheet Summary Dashboard
B2: KAVIN TRAVELS — Quality Assurance & Security Audit Dashboard
B3: Application Audit, Vulnerability Remediation, Test Execution & Verification Summary | October 2026
B5: Bug Metrics | C5: Count | E5: Testing Performance | F5: Count | H5: Audit Verdict
B6: Total Bugs Found | C6: =COUNTA('Bug Tracker'!A2:A100) | E6: Total Manual Test Cases | F6: =COUNTA('Manual Test Cases'!A2:A100) | H6: APPLICATION STATUS
B7: Critical Bugs | C7: =COUNTIF('Bug Tracker'!I2:I100, "Critical") | E7: Manual Tests Passed | F7: =COUNTIF('Manual Test Cases'!I2:I100, "Pass") | H7: PASS / STABILIZED
B8: High-Severity Bugs | C8: =COUNTIF('Bug Tracker'!I2:I100, "High") | E8: Manual Tests Failed | F8: =COUNTIF('Manual Test Cases'!I2:I100, "Fail")
B9: Medium-Severity Bugs | C9: =COUNTIF('Bug Tracker'!I2:I100, "Medium") | E9: Manual Tests Not Executed | F9: =COUNTIF('Manual Test Cases'!I2:I100, "Not Executed") | H9: OVERALL FIX RATE
B10: Low-Severity Bugs | C10: =COUNTIF('Bug Tracker'!I2:I100, "Low") | E10: Total Automated Tests | F10: =COUNTA('Automated Test Results'!A2:A100) | H10: 100.0%
B11: Bugs Fixed & Verified | C11: =COUNTIF('Bug Tracker'!P2:P100, "Fixed") | E11: Automated Tests Passed | F11: =COUNTIF('Automated Test Results'!H2:H100, "Passed")
B12: Open Bugs | C12: =COUNTIF('Bug Tracker'!P2:P100, "Open") | E12: Automated Tests Failed | F12: =COUNTIF('Automated Test Results'!H2:H100, "Failed") | H12: AUTOMATED PASS RATE
B13: Partially Fixed Bugs | C13: =COUNTIF('Bug Tracker'!P2:P100, "Partially Fixed") | E13: Automated Tests Skipped | F13: =COUNTIF('Automated Test Results'!H2:H100, "Skipped") | H13: 100.0% (25/25)
B14: Retest Required | C14: =COUNTIF('Bug Tracker'!P2:P100, "Retest Required") | E14: Security Audit Findings | F14: =COUNTA('Security Audit'!A2:A100)
B15: Blocked Issues | C15: =COUNTIF('Bug Tracker'!P2:P100, "Blocked") | E15: Security Remediations Verified | F15: =COUNTIF('Security Audit'!J2:J100, "Fixed")
B18: Severity | C18: Count | E18: Status | F18: Count | H18: Testing Category | I18: Passed | J18: Failed
B19: Critical | C19: =COUNTIF('Bug Tracker'!I2:I100, "Critical") | E19: Fixed | F19: =COUNTIF('Bug Tracker'!P2:P100, "Fixed") | H19: Manual Tests | I19: =COUNTIF('Manual Test Cases'!I2:I100, "Pass") | J19: =COUNTIF('Manual Test Cases'!I2:I100, "Fail")
B20: High | C20: =COUNTIF('Bug Tracker'!I2:I100, "High") | E20: Open | F20: =COUNTIF('Bug Tracker'!P2:P100, "Open") | H20: Automated Tests | I20: =COUNTIF('Automated Test Results'!H2:H100, "Passed") | J20: =COUNTIF('Automated Test Results'!H2:H100, "Failed")
B21: Medium | C21: =COUNTIF('Bug Tracker'!I2:I100, "Medium") | E21: Blocked | F21: =COUNTIF('Bug Tracker'!P2:P100, "Blocked")
B22: Low | C22: =COUNTIF('Bug Tracker'!I2:I100, "Low")

Sheet Bug Tracker
A1: Bug ID | B1: Date Found | C1: Module | D1: Bug Title | E1: Bug Description | F1: Reproduction Steps | G1: Expected Result | H1: Actual Result | I1: Severity | J1: Priority | K1: Root Cause | L1: Fix Applied | M1: Files Changed | N1: Test Case ID | O1: Test Evidence | P1: Fix Status | Q1: Retest Result | R1: Date Fixed | S1: Verified By | T1: Remarks
A2: BUG-001 | B2: 2026-10-03 | C2: Backend Config | D2: Plaintext root database password in application.properties | E2: Root MySQL password (nivak@0328) was committed in application.properties source code. | F2: Open backend/src/main/resources/application.properties and inspect line 15. | G2: Database passwords must be externalized via environment variables. | H2: Root password was committed directly in plaintext to version control. | I2: Critical | J2: P0 | K2: Hardcoded fallback in properties file. | L2: Replaced password default with ${DB_PASSWORD} without sensitive fallback; created sanitized application-example.properties. | M2: application.properties, application-example.properties | N2: TC-MAN-001 | O2: Properties inspected, verified parameterized | P2: Fixed | Q2: Pass | R2: 2026-10-03 | S2: Security Auditor | T2: Eliminated high-risk credential leak.
A3: BUG-002 | B3: 2026-10-03 | C3: Booking API | D3: IDOR vulnerability on /api/bookings/user/{userId} | E3: Any authenticated customer could query another customer's complete trip history by providing their numeric userId in the URL. | F3: Log in as Customer A. Send GET /api/bookings/user/2 with Customer A's JWT token. | G3: Access denied (403 Forbidden) when requesting other users' trip history. | H3: Server returned Customer B's complete bookings with status 200 OK. | I3: High | J3: P1 | K3: Controller and service lacked caller identity verification. | L3: Restricted /api/bookings/user/{userId} to ADMIN and implemented /api/bookings/my self-service endpoint using SecurityContext email. | M3: BookingController.java, BookingService.java, my-bookings.js | N3: TC-MAN-020 | O3: Unit test & my-bookings.js verified | P3: Fixed | Q3: Pass | R3: 2026-10-03 | S3: Security Auditor | T3: IDOR fully closed; customer UI updated to use /my.
A4: BUG-003 | B4: 2026-10-03 | C4: Booking API | D4: IDOR vulnerability on GET /api/bookings/{id} | E4: Any authenticated customer could view any booking itinerary in the database by guessing or enumerating IDs. | F4: Log in as Customer B. Send GET /api/bookings/1 (Customer A's booking). | G4: Access denied (403 Forbidden) when booking does not belong to caller. | H4: Server returned full booking details including customer contact information. | I4: High | J4: P1 | K4: Service retrieved entity by ID without checking if caller owns it. | L4: Added ownership verification in BookingService.getBookingById: checks caller ID or ROLE_ADMIN before returning DTO. | M4: BookingController.java, BookingService.java | N4: TC-MAN-017 | O4: BookingServiceTest.testGetBookingById_WrongUser_ThrowsUnauthorized passed | P4: Fixed | Q4: Pass | R4: 2026-10-03 | S4: Security Auditor | T4: Verified via automated security test.
A5: BUG-004 | B5: 2026-10-03 | C5: Booking API | D5: Global booking repository exposed to all customers | E5: GET /api/bookings was accessible to any authenticated customer, exposing all global system bookings. | F5: Log in as regular customer. Send GET /api/bookings. | G5: Only administrators should be able to view all bookings globally. | H5: All system bookings returned to regular customer. | I5: High | J5: P1 | K5: Missing @PreAuthorize annotation on controller endpoint. | L5: Added @PreAuthorize('hasRole("ADMIN")') on BookingController.getAllBookings(). | M5: BookingController.java | N5: TC-MAN-026 | O5: SecurityConfig & Controller test verified | P5: Fixed | Q5: Pass | R5: 2026-10-03 | S5: Security Auditor | T5: Restricted to ADMIN role.
A6: BUG-005 | B6: 2026-10-03 | C6: User API | D6: User directory exposed to regular customers | E6: GET /api/users was accessible to any authenticated user, exposing full names, emails, and phone numbers. | F6: Log in as regular customer. Send GET /api/users. | G6: Customer directory should only be accessible by administrators. | H6: Full user directory returned with status 200 OK. | I6: High | J6: P1 | K6: Missing role check on UserController.getAllUsers(). | L6: Added @PreAuthorize('hasRole("ADMIN")') on UserController.getAllUsers(). | M6: UserController.java | N6: TC-MAN-027 | O6: PreAuthorize enforced and verified | P6: Fixed | Q6: Pass | R6: 2026-10-03 | S6: Security Auditor | T6: Directory access locked down.
A7: BUG-006 | B7: 2026-10-03 | C7: User API | D7: IDOR vulnerability on GET /api/users/{id} | E7: Any authenticated customer could view another customer's profile by changing the ID in the URL. | F7: Log in as Customer B. Send GET /api/users/1. | G7: Customer should only view their own profile unless role is ADMIN. | H7: Returned Customer A's profile with personal contact data. | I7: High | J7: P1 | K7: UserService did not compare caller email with target user ID. | L7: Enforced ownership validation in UserService.getUserById; permits only self or ROLE_ADMIN. | M7: UserController.java, UserService.java | N7: TC-MAN-006 | O7: UserServiceTest passed | P7: Fixed | Q7: Pass | R7: 2026-10-03 | S7: Security Auditor | T7: Verified via UserServiceTest.
A8: BUG-007 | B8: 2026-10-03 | C8: Payment API | D8: Payment ledger & single payments exposed via IDOR | E8: GET /api/payments and GET /api/payments/{id} were accessible to any authenticated user without ownership validation. | F8: Log in as Customer B. Request GET /api/payments or GET /api/payments/{paymentA_id}. | G8: Global payments restricted to ADMIN; individual payment restricted to booking owner or ADMIN. | H8: Any customer could inspect any transaction amount and receipt. | I8: High | J8: P1 | K8: Missing @PreAuthorize on getAllPayments and missing owner check on getPaymentById. | L8: Restricted getAllPayments to ADMIN; added booking ownership check in PaymentService.getPaymentById. | M8: PaymentController.java, PaymentService.java | N8: TC-MAN-019 | O8: PaymentServiceTest passed | P8: Fixed | Q8: Pass | R8: 2026-10-03 | S8: Security Auditor | T8: Financial records secured.
A9: BUG-008 | B9: 2026-10-03 | C9: Payment API | D9: Payment processing permitted for unowned bookings | E9: POST /api/payments allowed any authenticated customer to record a payment against any arbitrary bookingId. | F9: Log in as Customer B. Send POST /api/payments with bookingId belonging to Customer A. | G9: Reject payment creation with 403 Forbidden when caller does not own the booking. | H9: Payment was saved and associated with Customer A's booking without authorization. | I9: High | J9: P1 | K9: PaymentService did not verify caller matches booking.getUser(). | L9: Added caller ownership validation in PaymentService.processPayment: throws UnauthorizedException if user mismatch. | M9: PaymentController.java, PaymentService.java | N9: TC-MAN-019 | O9: PaymentServiceTest.testProcessPayment_CustomerBPayForCustomerABooking passed | P9: Fixed | Q9: Pass | R9: 2026-10-03 | S9: Security Auditor | T9: Cross-customer payment tampering prevented.
A10: BUG-009 | B10: 2026-10-03 | C10: Payment API | D10: Client payload trusted for payment status (tampering) | E10: POST /api/payments accepted 'paymentStatus' from request body, allowing clients to self-mark payments as SUCCESSFUL. | F10: Send POST /api/payments with 'paymentStatus': 'SUCCESSFUL' in JSON body. | G10: Payment status should be controlled exclusively by server/gateway, defaulting to INITIATED. | H10: Backend blindly persisted client-provided paymentStatus. | I10: High | J10: P1 | K10: Builder copied req.getPaymentStatus() without backend verification. | L10: Backend forces paymentStatus to PaymentStatus.INITIATED on creation unconditionally. | M10: PaymentService.java | N10: TC-MAN-018 | O10: PaymentServiceTest.testProcessPayment_IgnoresClientPaymentStatus passed | P10: Fixed | Q10: Pass | R10: 2026-10-03 | S10: Security Auditor | T10: Eliminated payment status spoofing.
A11: BUG-010 | B11: 2026-10-03 | C11: Database / JPA | D11: JPQL query string comparison mismatch for CANCELLED status | E11: BookingRepository existsByCarIdAndPickupDateAndNotCancelled used string 'CANCELLED' but DB stores lowercase 'cancelled'. | F11: Book a car, cancel it, then attempt to book it again on the same date. | G11: Cancelled booking should not block new booking on that date. | H11: JPQL query failed to exclude cancelled bookings due to case mismatch. | I11: Medium | J11: P2 | K11: Literal string used in JPQL query instead of enum parameter handled by converter. | L11: Parameterized query with BookingStatus cancelledStatus enum parameter directly. | M11: BookingRepository.java, BookingService.java, CarAvailabilityService.java | N11: TC-MAN-014 | O11: BookingServiceTest and CarAvailabilityService verified | P11: Fixed | Q11: Pass | R11: 2026-10-03 | S11: QA Engineer | T11: Query now evaluates enum status properly.
A12: BUG-011 | B12: 2026-10-03 | C12: Database / Enum | D12: Database schema contains 'local_hourly' but Java enum lacks it | E12: Schema defines ENUM('one_way', 'round_trip', 'local_hourly') but TripType Java enum has MULTI_DAY instead. | F12: Read existing DB row with trip_type='local_hourly'. | G12: Application should parse record safely without throwing IllegalArgumentException. | H12: TripTypeConverter threw exception for 'local_hourly'. | I12: Medium | J12: P2 | K12: Schema and Java enum divergence during refactoring. | L12: Added safe fallback in TripTypeConverter to map 'LOCAL_HOURLY' to ONE_WAY and documented DB mismatch. | M12: TripTypeConverter.java | N12: TC-MAN-012 | O12: TripTypeConverter unit verified | P12: Fixed | Q12: Pass | R12: 2026-10-03 | S12: QA Engineer | T12: Backward-compatibility guaranteed.
... A16: BUG-018 | B16: 2026-10-03 | C16: Frontend Auth | D16: Broken 401 redirect from /admin/ subdirectory pages | E16: In api.js, 401 response handler redirected to relative 'admin-login.html', causing 404 when triggered from nested routes. | F16: Simulate token expiry while on an admin subdirectory page. | G16: Browser navigates reliably to the admin login page. | H16: Browser attempted to load non-existent relative paths. | I16: Low | J16: P3 | K16: Hardcoded relative URL strings in handleResponse. | L16: Constructed absolute redirect URL using window.location.origin. | M16: frontend/js/api.js | N16: TC-MAN-030 | O16: Browser navigation check verified | P16: Fixed | Q16: Pass | R16: 2026-10-03 | S16: Frontend QA | T16: Redirect functions correctly from all directories.

Sheet Manual Test Cases
A1: Test Case ID | B1: Module | C1: Test Scenario | D1: Preconditions | E1: Test Steps | F1: Test Data | G1: Expected Result | H1: Actual Result | I1: Status | J1: Related Bug ID | K1: Evidence | L1: Remarks
A2: TC-MAN-001 | B2: Auth | C2: Register with unique credentials | D2: Unregistered user | E2: 1. Open register.html 2. Fill name, email, password, phone 3. Submit | F2: Name: Tester, Email: new@test.com | G2: Account created, token stored | H2: Account created, token stored | I2: Pass | J2: - | K2: sessionStorage km_token verified | L2: Core customer signup flow
A3: TC-MAN-002 | B3: Auth | C3: Register with duplicate email | D3: Email exists | E3: 1. Fill register form with duplicate email 2. Submit | F3: Email: custA@example.com | G3: HTTP 409 Conflict, error toast | H3: HTTP 409 Conflict, error toast shown | I3: Pass | J3: - | K3: DuplicateResourceException caught | L3: Negative test
A4: TC-MAN-003 | B4: Auth | C4: Register with duplicate phone | D4: Phone exists | E4: 1. Fill register form with duplicate phone 2. Submit | F4: Phone: 9876543210 | G4: HTTP 409 Conflict, error toast | H4: HTTP 409 Conflict, error toast shown | I4: Pass | J4: - | K4: DuplicateResourceException caught | L4: Negative test
A5: TC-MAN-004 | B5: Auth | C5: Login with valid credentials | D5: Registered account | E5: 1. Enter email/password 2. Submit | F5: custA@example.com / Pass123! | G5: Token issued, user name in navbar | H5: Token issued, user name in navbar | I5: Pass | J5: - | K5: LoginResponseDTO received | L5: Happy path auth
A6: TC-MAN-005 | B6: Auth | C6: Login with invalid password | D6: Registered account | E6: 1. Enter valid email and wrong password 2. Submit | F6: WrongPass! | G6: HTTP 401 Unauthorized | H6: HTTP 401 Unauthorized | I6: Pass | J6: - | K6: BadCredentialsException handled | L6: Security test
A7: TC-MAN-006 | B7: Auth | C7: Customer session logout | D7: Logged in | E7: 1. Click Logout in navbar | F7: - | G7: Token removed, redirect to home | H7: Token removed, redirect to home | I7: Pass | J7: - | K7: sessionStorage cleared | L7: Session management
A8: TC-MAN-007 | B8: Catalog | C8: Browse fleet catalog | D8: Backend up | E8: 1. Open index.html / cars.html | F8: - | G8: Car cards rendered with price/km | H8: All cars loaded dynamically | I8: Pass | J8: - | K8: GET /api/cars 200 OK | L8: Public catalog
A9: TC-MAN-008 | B9: Booking | C9: Select pickup location from Tamil Nadu dataset | D9: On booking.html | E9: 1. Type 'Coimbatore' 2. Pick from dropdown | F9: Pickup: Coimbatore | G9: Marker placed, address set | H9: Marker placed, address set | I9: Pass | J9: - | K9: LocationSelector initialized | L9: Location picker
A10: TC-MAN-009 | B10: Booking | C10: Select dropoff destination & route plot | D10: Pickup set | E10: 1. Type 'Ooty' 2. Pick from dropdown | F10: Dropoff: Ooty | G10: Polyline drawn, distance ~86km | H10: Route displayed, ~86km distance | I10: Pass | J10: - | K10: Leaflet map route rendered | L10: Routing test
A11: TC-MAN-010 | B11: Booking | C11: Select identical pickup and dropoff | D11: On booking.html | E11: 1. Select Coimbatore for both | F11: Coimbatore to Coimbatore | G11: Warning alert / 0 km boundary notice | H11: Warning alert / 0 km boundary notice | I11: Pass | J11: - | K11: Form boundary check | L11: Boundary test
A12: TC-MAN-011 | B12: Booking | C12: Swap pickup and dropoff locations | D12: Route selected | E12: 1. Click swap button | F12: - | G12: Pickup and dropoff reversed | H12: Locations reversed on map and form | I12: Pass | J12: - | K12: UI state inversion | L12: Usability test
... A31: TC-MAN-030 | B31: Session | C31: 401 session expiry redirect from admin page | D31: Expired token | E31: 1. Trigger 401 on admin page | F31: - | G31: Redirects to absolute admin-login.html | H31: Redirects to absolute admin-login.html | I31: Pass | J31: BUG-018 | K31: window.location.origin used | L31: Navigation bug fix

Sheet Automated Test Results
A1: Test ID | B1: Test Suite | C1: Test Name | D1: Test Type | E1: Execution Date | F1: Expected Result | G1: Actual Result | H1: Status | I1: Related Bug ID | J1: Evidence | K1: Remarks
A2: AUT-001 | B2: JwtServiceTest | C2: testGenerateAndParseToken | D2: Unit / Security | E2: 2026-10-03 | F2: Valid 3-part JWT generated and parsed | G2: Token parsed with exact subject; validated | H2: Passed | I2: - | J2: BUILD SUCCESS in 0.174s | K2: JJWT signing & verification
A3: AUT-002 | B3: JwtServiceTest | C3: testValidateToken_TamperedToken_ReturnsFalse | D3: Unit / Security | E3: 2026-10-03 | F3: Tampered signature fails validation | G3: Signature validation failed safely (false) | H3: Passed | I3: - | J3: SignatureException caught | K3: Cryptographic verification
A4: AUT-003 | B4: JwtServiceTest | C4: testValidateToken_MalformedString_ReturnsFalse | D4: Unit / Security | E4: 2026-10-03 | F4: Garbage string returns false | G4: Returned false cleanly without uncaught crash | H4: Passed | I4: - | J4: MalformedJwtException caught | K4: Input robustness
A5: AUT-004 | B5: AuthServiceTest | C5: testRegister_Success | D5: Unit | E5: 2026-10-03 | F5: New user registered and JWT token issued | G5: User saved with BCrypt hash; JWT issued | H5: Passed | I5: - | J5: LoginResponseDTO verified | K5: Registration happy path
A6: AUT-005 | B6: AuthServiceTest | C6: testRegister_DuplicateEmail_ThrowsDuplicateResource | D6: Unit / Negative | E6: 2026-10-03 | F6: Duplicate email throws DuplicateResourceException | G6: DuplicateResourceException thrown and verified | H6: Passed | I6: - | J6: ExistsByEmail check verified | K6: Data integrity
A7: AUT-006 | B7: AuthServiceTest | C7: testRegister_DuplicatePhone_ThrowsDuplicateResource | D7: Unit / Negative | E7: 2026-10-03 | F7: Duplicate phone throws DuplicateResourceException | G7: DuplicateResourceException thrown and verified | H7: Passed | I7: - | J7: ExistsByPhone check verified | K7: Data integrity
A8: AUT-007 | B8: AuthServiceTest | C8: testLogin_Success | D8: Unit | E8: 2026-10-03 | F8: Valid credentials authenticate and return token | G8: Token issued with Bearer type | H8: Passed | I8: - | J8: AuthenticationManager verified | K8: Login happy path
A9: AUT-008 | B9: BookingServiceTest | C9: testCreateBooking_PastDate_ThrowsInvalidBookingException | D9: Unit / Security | E9: 2026-10-03 | F9: Past pickup date rejected with InvalidBookingException | G9: InvalidBookingException thrown: 'past' | H9: Passed | I9: BUG-012 | J9: AssertThrows InvalidBookingException | K9: Temporal validation fix
A10: AUT-009 | B10: BookingServiceTest | C10: testCreateBooking_CarAlreadyBooked_ThrowsCarUnavailable | D10: Unit / Concurrency | E10: 2026-10-03 | F10: Double booking rejected with CarUnavailableException | G10: CarUnavailableException thrown cleanly | H10: Passed | I10: BUG-010 | J10: existsByCarId query verified | K10: Resource conflict check
A11: AUT-010 | B11: BookingServiceTest | C11: testGetBookingById_WrongUser_ThrowsUnauthorized | D11: Unit / Security | E11: 2026-10-03 | F11: Unauthorized customer rejected with UnauthorizedException | G11: UnauthorizedException thrown: 'Access denied' | H11: Passed | I11: BUG-003 | J11: Caller ownership check verified | K11: IDOR fix verification
A12: AUT-011 | B12: BookingServiceTest | C12: testCancelBooking_AlreadyCompleted_ThrowsInvalidBookingException | D12: Unit / State | E12: 2026-10-03 | F12: Cancelling completed booking throws InvalidBookingException | G12: InvalidBookingException thrown: 'completed' | H12: Passed | I12: BUG-019 | J12: State machine check verified | K12: Business rule enforcement
... A26: AUT-025 | B26: BookingControllerTest | C26: testGetAllBookingsEndpoint | D26: Integration / WebMvc | E26: 2026-10-03 | F26: GET /api/bookings returns 200 OK with booking list | G26: Status 200 OK, JSON array serialized | H26: Passed | I26: - | J26: MockMvc result verified | K26: Admin endpoint verification

Sheet Security Audit
A1: Security Finding ID | B1: Component | C1: Finding | D1: Risk | E1: Severity | F1: Evidence | G1: Recommended Fix | H1: Fix Applied | I1: Retest Result | J1: Status | K1: Remarks
A2: SEC-001 | B2: Configuration | C2: Plaintext MySQL password in application.properties | D2: Direct database takeover upon code leak | E2: Critical | F2: spring.datasource.password=nivak@0328 in Git | G2: Externalize to DB_PASSWORD env variable | H2: Removed password; set ${DB_PASSWORD} with no default | I2: Pass | J2: Fixed | K2: Credential eliminated from repo
A3: SEC-002 | B3: Authentication | C3: Hardcoded default administrator credentials | D3: Instant root administrative takeover via known login | E3: Critical | F3: kavinmuthu84@gmail.com / kavinhari@03 hardcoded in Java | G3: Require explicit env vars or manual DB seeding | H3: Seeding skipped unless ADMIN_EMAIL and ADMIN_PASSWORD env vars provided | I3: Pass | J3: Fixed | K3: Eliminated hardcoded backdoor
A4: SEC-003 | B4: User Management | C4: IDOR on user profile fetch (/api/users/{id}) | D4: Customer PII exposure (email, phone, name) | E4: High | F4: Any user token could retrieve any user profile | G4: Verify caller identity or ADMIN role | H4: Enforced ownership check in UserService.getUserById | I4: Pass | J4: Fixed | K4: Covered in UserServiceTest
A5: SEC-004 | B5: Bookings | C5: IDOR & global booking repository exposure | D5: Full travel itinerary and customer data harvesting | E5: High | F5: /api/bookings returned all bookings; /{id} had no owner check | G5: Restrict to ADMIN and check booking ownership | H5: getAllBookings made ADMIN-only; added /api/bookings/my; added owner check on /{id} | I5: Pass | J5: Fixed | K5: Covered in BookingServiceTest
A6: SEC-005 | B6: User Management | C6: Unrestricted user directory endpoint (/api/users) | D6: Complete customer database enumeration | E6: High | F6: GET /api/users open to all logged-in customers | G6: Restrict to ADMIN role | H6: Added @PreAuthorize('hasRole("ADMIN")') | I6: Pass | J6: Fixed | K6: Directory restricted
A7: SEC-006 | B7: Payments | C7: Insecure payment ledger and IDOR on /api/payments/{id} | D7: Financial record and amount exposure | E7: High | F7: GET /api/payments accessible to any authenticated user | G7: Restrict to ADMIN role and verify payment ownership | H7: getAllPayments restricted to ADMIN; getPaymentById checks booking ownership | I7: Pass | J7: Fixed | K7: Covered in PaymentServiceTest
A8: SEC-007 | B8: Payments | C8: Client-side payment status forgery | D8: Fraudulent bookings confirmed without payment | E8: High | F8: POST /api/payments trusted client paymentStatus: SUCCESSFUL | G8: Enforce server-side state transitions | H8: Backend forces status to INITIATED on creation unconditionally | I8: Pass | J8: Fixed | K8: Covered in PaymentServiceTest
A9: SEC-008 | B9: Payments | C9: Payment submission for arbitrary bookings | D9: Payment records created against unauthorized bookings | E9: High | F9: processPayment did not check caller owns booking | G9: Verify booking.getUser().equals(caller) | H9: Added caller ownership validation in PaymentService | I9: Pass | J9: Fixed | K9: Covered in PaymentServiceTest
A10: SEC-009 | B10: Error Handling | C10: Server stack trace and SQL query leakage on 500 error | D10: Reconnaissance data for targeted exploits | E10: Medium | F10: ex.getMessage() returned in JSON response body | G10: Sanitize error responses; log details on server | H10: Generic error returned to client; full trace logged with log.error() | I10: Pass | J10: Fixed | K10: GlobalExceptionHandler updated
A11: SEC-010 | B11: Configuration | C11: SQL query logging enabled in production configuration | D11: Sensitive parameters and structure logged to disk | E11: Low | F11: spring.jpa.show-sql=true in properties | G11: Disable SQL logging in production | H11: Changed to spring.jpa.show-sql=false | I11: Pass | J11: Fixed | K11: Reduced log bloat and risk
A12: SEC-011 | B12: Configuration | C12: Hibernate Open-In-View enabled | D12: Connection starvation and N+1 query vulnerability | E12: Low | F12: spring.jpa.open-in-view=true in properties | G12: Disable OSIV for strict transactional boundary | H12: Changed to spring.jpa.open-in-view=false | I12: Pass | J12: Fixed | K12: Best practice architecture
